iiitb_mux.v
module iiitb_mux(out, a, b, c, d, s0, s1);

output out;
input a, b, c, d, s0, s1;
wire sobar, s1bar, T1, T2, T3, T4;

not (s0bar, s0), (s1bar, s1);
and (T1, a, s0bar, s1bar), (T2, b, s0bar, s1),(T3, c, s0, s1bar), (T4, d, s0, s1);
or(out, T1, T2, T3, T4);

endmodule

iiitb_mux_tb.v
module top;

wire  out;
reg  a;
reg  b;
reg  c;
reg  d;
reg s0, s1;

iiitb_mux name(.out(out), .a(a), .b(b), .c(c), .d(d), .s0(s0), .s1(s1));
initial
 begin
 $dumpfile("test.vcd");
 $dumpvars(0,top);
 a=1'b0; b=1'b0; c=1'b0; d=1'b0;
 s0=1'b0; s1=1'b0;
 #500 $finish;

 end

always #40 a=~a;
always #20 b=~b;
always #10 c=~c;
always #5 d=~d;
always #80 s0=~s0;
always #160 s1=~s1;

always@(a or b or c or d or s0 or s1) 
$monitor("At time = %t, Output = %d", $time, out);

endmodule

test.vcd
$date
	Fri Oct  7 22:36:41 2022
$end
$version
	Icarus Verilog
$end
$timescale
	1s
$end
$scope module top $end
$var wire 1 ! out $end
$var reg 1 " a $end
$var reg 1 # b $end
$var reg 1 $ c $end
$var reg 1 % d $end
$var reg 1 & s0 $end
$var reg 1 ' s1 $end
$scope module name $end
$var wire 1 ( T1 $end
$var wire 1 ) T2 $end
$var wire 1 * T3 $end
$var wire 1 + T4 $end
$var wire 1 " a $end
$var wire 1 # b $end
$var wire 1 $ c $end
$var wire 1 % d $end
$var wire 1 ! out $end
$var wire 1 & s0 $end
$var wire 1 , s0bar $end
$var wire 1 ' s1 $end
$var wire 1 - s1bar $end
$upscope $end
$upscope $end
$enddefinitions $end
#0
$dumpvars
1-
1,
0+
0*
0)
0(
0'
0&
0%
0$
0#
0"
0!
$end
#5
1%
#10
0%
1$
#15
1%
#20
0%
0$
1#
#25
1%
#30
0%
1$
#35
1%
#40
1!
1(
0%
0$
0#
1"
#45
1%
#50
0%
1$
#55
1%
#60
0%
0$
1#
#65
1%
#70
0%
1$
#75
1%
#80
0!
0(
0,
0%
0$
0#
0"
1&
#85
1%
#90
1!
1*
0%
1$
#95
1%
#100
0!
0*
0%
0$
1#
#105
1%
#110
1!
1*
0%
1$
#115
1%
#120
0!
0*
0%
0$
0#
1"
#125
1%
#130
1!
1*
0%
1$
#135
1%
#140
0!
0*
0%
0$
1#
#145
1%
#150
1!
1*
0%
1$
#155
1%
#160
0!
1,
0*
0-
0%
0$
0#
0"
0&
1'
#165
1%
#170
0%
1$
#175
1%
#180
1!
1)
0%
0$
1#
#185
1%
#190
0%
1$
#195
1%
#200
0!
0)
0%
0$
0#
1"
#205
1%
#210
0%
1$
#215
1%
#220
1!
1)
0%
0$
1#
#225
1%
#230
0%
1$
#235
1%
#240
0!
0)
0,
0%
0$
0#
0"
1&
#245
1!
1+
1%
#250
0!
0+
0%
1$
#255
1!
1+
1%
#260
0!
0+
0%
0$
1#
#265
1!
1+
1%
#270
0!
0+
0%
1$
#275
1!
1+
1%
#280
0!
0+
0%
0$
0#
1"
#285
1!
1+
1%
#290
0!
0+
0%
1$
#295
1!
1+
1%
#300
0!
0+
0%
0$
1#
#305
1!
1+
1%
#310
0!
0+
0%
1$
#315
1!
1+
1%
#320
0!
1,
1-
0+
0%
0$
0#
0"
0&
0'
#325
1%
#330
0%
1$
#335
1%
#340
0%
0$
1#
#345
1%
#350
0%
1$
#355
1%
#360
1!
1(
0%
0$
0#
1"
#365
1%
#370
0%
1$
#375
1%
#380
0%
0$
1#
#385
1%
#390
0%
1$
#395
1%
#400
0!
0(
0,
0%
0$
0#
0"
1&
#405
1%
#410
1!
1*
0%
1$
#415
1%
#420
0!
0*
0%
0$
1#
#425
1%
#430
1!
1*
0%
1$
#435
1%
#440
0!
0*
0%
0$
0#
1"
#445
1%
#450
1!
1*
0%
1$
#455
1%
#460
0!
0*
0%
0$
1#
#465
1%
#470
1!
1*
0%
1$
#475
1%
#480
0!
1,
0*
0-
0%
0$
0#
0"
0&
1'
#485
1%
#490
0%
1$
#495
1%
#500
1!
1)
0%
0$
1#
